LICENSE
README.md
dist-readme.md
requirements.txt
interface_gen/.flake8
interface_gen/README.md
interface_gen/__init__.py
interface_gen/docs.py
interface_gen/generate.py
interface_gen/protocols_test.py
interface_gen/toolchain.py
interface_gen-0.1.0.dist-info/METADATA
interface_gen-0.1.0.dist-info/WHEEL
interface_gen-0.1.0.dist-info/entry_points.txt
interface_gen-0.1.0.dist-info/licenses/LICENSE
interface_gen-0.1.0.dist-info/RECORD
