Metadata-Version: 2.4
Name: interface_gen
Version: 0.1.0
Summary: Define data format schemas once and generate code for multiple languages and serialization frameworks.
Project-URL: Homepage, https://github.com/getditto/interface-gen
Project-URL: Issues, https://github.com/getditto/interface-gen/issues
Author-email: Aaron Fabbri <aaron.fabbri@ditto.live>
License-File: LICENSE
Classifier: Development Status :: 4 - Beta
Classifier: License :: OSI Approved :: Apache Software License
Classifier: Operating System :: POSIX :: Linux
Classifier: Programming Language :: Python :: 3
Classifier: Topic :: File Formats
Requires-Python: >=3.10
Requires-Dist: avro==1.11.3
Requires-Dist: avrotize==2.6.0
Requires-Dist: fastavro==1.9.7
Requires-Dist: flake8==7.1.1
Requires-Dist: install-jdk==1.1.0
